django_model_versioning/lib/__init__.py
django_model_versioning/lib/apps.py
django_model_versioning/lib/config.py
django_model_versioning/lib/core.py
django_model_versioning/lib/fields.py
django_model_versioning/lib/register.py
django_model_versioning/lib/signals.py
django_model_versioning/lib/types.py
django_model_versioning/lib/versioned_foreign_key.py
django_model_versioning/lib/versioned_model.py
django_model_versioning/lib/versioning_field.py
django_model_versioning/lib/versioning_options.py
django_model_versioning-0.1.1.dist-info/LICENSE
django_model_versioning-0.1.1.dist-info/METADATA
django_model_versioning-0.1.1.dist-info/WHEEL
django_model_versioning-0.1.1.dist-info/RECORD
