Metadata-Version: 2.1
Name: django-model-versioning
Version: 0.1.1
Summary: A library to version a specific model, with references to specific and/or last version of it
Home-page: https://github.com/tavearn/django-model-versioning
License: GPLv3
Author: Emanuele Manfredini
Author-email: emanuele.manfredini.1992@gmail.com
Requires-Python: >=3.12,<4.0
Classifier: Development Status :: 5 - Production/Stable
Classifier: Framework :: Django
Classifier: Framework :: Django :: 5.0
Classifier: Intended Audience :: Developers
Classifier: License :: OSI Approved :: GNU General Public License v3 (GPLv3)
Classifier: License :: Other/Proprietary License
Classifier: Operating System :: OS Independent
Classifier: Programming Language :: Python
Classifier: Programming Language :: Python :: 3
Classifier: Programming Language :: Python :: 3.12
Classifier: Topic :: Software Development :: Libraries
Classifier: Topic :: Software Development :: Libraries :: Python Modules
Requires-Dist: Django (>=5.0.0,<6.0.0)
Project-URL: Repository, https://github.com/tavearn/django-model-versioning
